{
  "version": "7",
  "dialect": "postgresql",
  "entries": [
    {
      "idx": 0,
      "version": "7",
      "when": 1742153514882,
      "tag": "0000_dashing_gambit",
      "breakpoints": true
    },
    {
      "idx": 1,
      "version": "7",
      "when": 1747639470911,
      "tag": "0001_yielding_smiling_tiger",
      "breakpoints": true
    },
    {
      "idx": 2,
      "version": "7",
      "when": 1747639609607,
      "tag": "0002_uneven_callisto",
      "breakpoints": true
    }
  ]
}